<?xml version="1.0" encoding="UTF-8"?><record_update table="ua_table_licensing_config">
    <ua_table_licensing_config action="INSERT_OR_UPDATE">
        <is_fulfillment>false</is_fulfillment>
        <license_condition/>
        <license_model>none</license_model>
        <license_roles/>
        <name>x_800383_ajanta_x_test_datasource</name>
        <op_delete>true</op_delete>
        <op_insert>true</op_insert>
        <op_update>true</op_update>
        <owner_condition/>
        <sys_class_name>ua_table_licensing_config</sys_class_name>
        <sys_created_by>admin</sys_created_by>
        <sys_created_on>2023-10-21 11:41:07</sys_created_on>
        <sys_id>fcc577e683090210bbeb31b6feaad39e</sys_id>
        <sys_mod_count>0</sys_mod_count>
        <sys_name>x_800383_ajanta_x_test_datasource</sys_name>
        <sys_package display_value="Ajanta X-Ray Clinic" source="x_800383_ajanta_x">8e8c37e497e9b110b1f27ca0f053afc7</sys_package>
        <sys_policy/>
        <sys_scope display_value="Ajanta X-Ray Clinic">8e8c37e497e9b110b1f27ca0f053afc7</sys_scope>
        <sys_update_name>ua_table_licensing_config_fcc577e683090210bbeb31b6feaad39e</sys_update_name>
        <sys_updated_by>admin</sys_updated_by>
        <sys_updated_on>2023-10-21 11:41:07</sys_updated_on>
    </ua_table_licensing_config>
</record_update>
